{
    "Version": "2008-10-17",
    "Statement": [
        {
            "Effect": "Allow",
            "Principal": "*",
            "Action": "s3:GetObject",
            "Resource": [
                "arn:aws:s3:::c11284a125440l1059271t1w997978499156-s3bucket-in539nl5qzjj/*",
                "arn:aws:s3:::c11284a125440l1059271t1w997978499156-s3bucket-in539nl5qzjj"
            ],
            "Condition": {
                "IpAddress": {
                    "aws:SourceIp": [
                        "0.0.0.0/0"
                    ]
                }
            }
        },
        {
            "Sid": "DenyOneObjectIfRequestNotSigned",
            "Effect": "Deny",
            "Principal": "*",
            "Action": "s3:GetObject",
            "Resource": "arn:aws:s3:::c11284a125440l1059271t1w997978499156-s3bucket-in539nl5qzjj/report.html",
            "Condition": {
                "StringNotEquals": {
                    "s3:authtype": "REST-QUERY-STRING"
                }
            }
        }
    ]
}